Metadata-Version: 2.0
Name: pynlg
Version: 0.1.1
Summary: Natural Language Generation in Python
Home-page: http://github.com/mapado/pynlg
Author: Jerry Nieuviarts
Author-email: jerry@mapado.com
License: MIT
Keywords: text realisation,pynlg,simplenlg
Platform: UNKNOWN
Classifier: Development Status :: 2 - Pre-Alpha
Classifier: Intended Audience :: Developers
Classifier: Natural Language :: English
Classifier: License :: OSI Approved :: MIT License
Classifier: Operating System :: OS Independent
Classifier: Programming Language :: Python
Classifier: Programming Language :: Python :: Implementation :: CPython
Classifier: Programming Language :: Python :: 2
Classifier: Programming Language :: Python :: 2.7
Classifier: Programming Language :: Python :: 3
Classifier: Programming Language :: Python :: 3.5
Classifier: Topic :: Software Development :: Libraries :: Python Modules
Classifier: Topic :: Text Processing :: Linguistic
Requires-Dist: six
